pytest_quilla/__init__.py
pytest_quilla/pytest_classes.py
quilla/__init__.py
quilla/__main__.py
quilla/_doc.py
quilla/ctx.py
quilla/py.typed
quilla/ui_validation.py
quilla/browser/__init__.py
quilla/browser/browser_validations.py
quilla/browser/drivers.py
quilla/common/__init__.py
quilla/common/enums.py
quilla/common/exceptions.py
quilla/common/utils.py
quilla/hookspecs/__init__.py
quilla/hookspecs/_hookspec.py
quilla/hookspecs/configuration.py
quilla/hookspecs/reports.py
quilla/hookspecs/steps.py
quilla/plugins/__init__.py
quilla/plugins/base_storage.py
quilla/plugins/blob_storage.py
quilla/plugins/local_storage.py
quilla/reports/__init__.py
quilla/reports/base_report.py
quilla/reports/report_summary.py
quilla/reports/step_failure_report.py
quilla/reports/validation_report.py
quilla/reports/visual_parity_report.py
quilla/steps/__init__.py
quilla/steps/base_steps.py
quilla/steps/outputs.py
quilla/steps/steps.py
quilla/steps/steps_aggregator.py
quilla/steps/validations/__init__.py
quilla/steps/validations/url.py
quilla/steps/validations/validation_factory.py
quilla/steps/validations/visual_parity.py
quilla/steps/validations/xpath.py
quilla-0.5.2.dist-info/LICENSE
quilla-0.5.2.dist-info/METADATA
quilla-0.5.2.dist-info/WHEEL
quilla-0.5.2.dist-info/entry_points.txt
quilla-0.5.2.dist-info/top_level.txt
quilla-0.5.2.dist-info/RECORD
