Metadata-Version: 2.1
Name: quilla
Version: 0.5.2
Summary: Declarative UI testing with JSON
Home-page: https://github.com/microsoft/quilla
Author: Natalia Maximo
Author-email: tal.afp.max@gmail.com
Maintainer: CRE Avengers
Maintainer-email: cre-avengers@microsoft.com
License: UNKNOWN
Project-URL: Issues, https://github.com/microsoft/quilla/issues
Project-URL: Discussions, https://github.com/microsoft/quilla/discussions
Platform: UNKNOWN
Classifier: Development Status :: 4 - Beta
Classifier: Environment :: Console
Classifier: Framework :: Pytest
Classifier: Intended Audience :: Developers
Classifier: License :: OSI Approved :: MIT License
Classifier: Operating System :: OS Independent
Classifier: Programming Language :: Python :: 3
Classifier: Programming Language :: Python :: 3.8
Classifier: Programming Language :: Python :: 3.9
Classifier: Programming Language :: Python :: 3.10
Classifier: Topic :: Software Development :: Quality Assurance
Classifier: Topic :: Software Development :: Testing
Classifier: Typing :: Typed
Requires-Python: >=3.8
Requires-Dist: selenium
Requires-Dist: pluggy
Requires-Dist: msedge-selenium-tools
Requires-Dist: pydeepmerge
Requires-Dist: pillow
Requires-Dist: azure-storage-blob
Provides-Extra: all
Requires-Dist: mypy ; extra == 'all'
Requires-Dist: pytest-cov ; extra == 'all'
Requires-Dist: sphinx ; extra == 'all'
Requires-Dist: sphinx-autodoc-typehints ; extra == 'all'
Requires-Dist: myst-parser ; extra == 'all'
Requires-Dist: types-setuptools ; extra == 'all'
Requires-Dist: flake8 ; extra == 'all'
Requires-Dist: pytest-xdist ; extra == 'all'
Requires-Dist: pre-commit ; extra == 'all'
Requires-Dist: gitchangelog ; extra == 'all'
Requires-Dist: pytest ; extra == 'all'
Requires-Dist: sphinx-rtd-theme ; extra == 'all'
Requires-Dist: twine ; extra == 'all'
Requires-Dist: sphinx-argparse-cli ; extra == 'all'
Requires-Dist: pytest-sugar ; extra == 'all'
Requires-Dist: wheel ; extra == 'all'
Requires-Dist: pystache ; extra == 'all'
Provides-Extra: dev
Requires-Dist: pre-commit ; extra == 'dev'
Requires-Dist: types-setuptools ; extra == 'dev'
Provides-Extra: docs
Requires-Dist: sphinx ; extra == 'docs'
Requires-Dist: sphinx-rtd-theme ; extra == 'docs'
Requires-Dist: sphinx-autodoc-typehints ; extra == 'docs'
Requires-Dist: myst-parser ; extra == 'docs'
Requires-Dist: sphinx-argparse-cli ; extra == 'docs'
Provides-Extra: pytest
Requires-Dist: pytest ; extra == 'pytest'
Provides-Extra: release
Requires-Dist: wheel ; extra == 'release'
Requires-Dist: twine ; extra == 'release'
Requires-Dist: gitchangelog ; extra == 'release'
Requires-Dist: pystache ; extra == 'release'
Provides-Extra: tests
Requires-Dist: flake8 ; extra == 'tests'
Requires-Dist: mypy ; extra == 'tests'
Requires-Dist: pytest ; extra == 'tests'
Requires-Dist: pytest-cov ; extra == 'tests'
Requires-Dist: pytest-sugar ; extra == 'tests'
Requires-Dist: pytest-xdist ; extra == 'tests'
